jmesflat/__init__.py
jmesflat/_clean.py
jmesflat/_flatten.py
jmesflat/_merge.py
jmesflat/_unflatten.py
jmesflat/constants.py
jmesflat/utils.py
jmesflat-0.1.2.dist-info/LICENSE
jmesflat-0.1.2.dist-info/WHEEL
jmesflat-0.1.2.dist-info/METADATA
jmesflat-0.1.2.dist-info/RECORD
