Metadata-Version: 2.1
Name: jmesflat
Version: 0.1.2
Summary: Flatten, unflatten, and merge deeply nested JSON objects using JMESPath notation.
Author-email: Sam Hartzog <sam.hartzog@hank.ai>
Requires-Python: >=3.10
Classifier: Programming Language :: Python :: 3 :: Only
Classifier: Programming Language :: Python :: 3.9
Classifier: Programming Language :: Python :: 3.10
Classifier: Programming Language :: Python :: 3.11
Classifier: Programming Language :: Python :: 3.12
Classifier: License :: OSI Approved :: MIT License
Classifier: Topic :: File Formats :: JSON
Requires-Dist: jmespath
Project-URL: Home, https://github.com/hank-ai/jmesflat
Project-URL: Issues, https://github.com/hank-ai/jmesflat/issues
